Workbook

Sheet Cover
A1: EUR Receivable Hedge Model — Technical Specification
A3: Created by | B3: Yumi Nagayoshi
A4: Date Created | B4: 2026-07-28
A5: Version | B5: 0.1 (draft)
A6: LLM Used | B6: Claude (Anthropic) — drafted from Stage 1 memo + scenarios.md, Scenario 1
A7: Role | B7: Treasury Analyst
A8: Audience | B8: CFO / Director of Treasury
A9: Companion document | B9: 2026-07-21-Nagayoshi-eur-receivable-solar-importer-hedge-framing.md (Stage 1 memo)
A11: Problem Statement
A12: The company (a U.S. solar equipment importer) holds a EUR-denominated receivable settling in one year. At today's spot rate, the receivable is worth approximately $4.5M USD-equivalent; a depreciation of EUR against USD over the horizon would reduce realized USD proceeds and compress the margin on the underlying sale. This workbook quantifies and compares four approaches — no hedge, forward hedge, money-market hedge, and option hedges (protective put and zero-cost-structured collar) — to support the hedge recommendation carried forward from the Stage 1 memo.
A14: Decision Context
A15: Treasury analysis for CFO review; deal terms are quoted by the counterparty bank (forward, put, call), and the money-market leg is priced off the company's own USD/EUR funding and investment rates.
A17: Data Sources & Access Dates
A18: • Spot, forward, and option premiums: counterparty bank quoted deal terms, scenarios.md Scenario 1 (market close near July 20-21, 2026).
A19: • R_USD placeholder: U.S. Treasury 1Y CMT or equivalent USD funding rate — to be refreshed at Stage 4 execution.
A20: • R_FC placeholder: 12-month Euribor — to be refreshed at Stage 4 execution.
A21: • All values in Section 2 (Inputs tab) are INDICATIVE placeholders, to be replaced with live market data at Stage 4.
A23: ⚠ Open Items Carried Into Stage 3
A24: 1. FC_AMT — CONFIRMED: the $4,500,000 receivable is today's USD-equivalent value, translated to EUR at spot (S0_in = 1.14). FC_AMT = 4,500,000 / 1.14 ≈ €3,947,368.
A25: 2. Forward-vs-parity gap (MoneyMarket tab) — verify the counterparty's quoted forward rather than assuming a model error.
A26: 3. Rate basis simplified to single ACT/360 for both legs; revisit if the EUR-side convention differs materially at execution.

Sheet Legend-Key
A1: Legend / Key
A3: Convention | B3: Meaning
A4: Yellow fill | B4: Input — hardcoded placeholder value, replaced with live market data at Stage 4
A5: Blue text | B5: Assumption / scenario lever (e.g. grid step size)
A6: Black text | B6: Formula — computed from named ranges, never hardcoded
A7: Green text | B7: Cross-tab link — pulls a value computed on another tab
A9: Note: fill color is used for input cells throughout the workbook (yellow). Blue/black/green are applied as font color on formula and link cells; the swatches above use fill only to make each convention visually distinct in this key.

Sheet Inputs
A1: Inputs — Named-Range Contract
A2: All values below are indicative — replaced with live market data at Stage 4. Rates and spot reflect market close near July 20-21, 2026; forward and option premiums are the counterparty's quoted deal terms.
A4: Named Range | B4: Description | C4: Unit | D4: Value | E4: Stage-4 Data Source
A5: FC_AMT | B5: EUR receivable notional | C5: EUR | D5: 3947368 | E5: Confirmed: $4,500,000 today's value / spot (1.14) = €3,947,368. Re-verify against signed sales agreement at Stage 4.
A6: S0_in | B6: Spot rate at inception | C6: USD per EUR | D6: 1.14 | E6: Live EURUSD spot, e.g. Bloomberg/Reuters, at execution
A7: F0_in | B7: Forward rate, 1-year | C7: USD per EUR | D7: 1.0875 | E7: Counterparty bank forward quote at execution
A8: R_USD | B8: USD interest rate | C8: Annual %, ACT/360 | D8: 0.0403 | E8: U.S. Treasury 1Y CMT (or equivalent USD funding rate) at execution
A9: R_FC | B9: EUR interest rate | C9: Annual %, ACT/360 | D9: 0.0288 | E9: 12-month Euribor at execution
A10: K_PUT | B10: Put option strike | C10: USD per EUR | D10: 1.14 | E10: Set at/near live spot at execution
A11: K_CALL | B11: Call option strike | C11: USD per EUR | D11: 1.14 | E11: Set at/near live spot at execution
A12: PREM_PUT | B12: Put premium per unit of FC | C12: USD | D12: 0.015 | E12: Counterparty option quote at execution
A13: PREM_CALL | B13: Call premium per unit of FC | C13: USD | D13: 0.018 | E13: Counterparty option quote at execution
A14: T_DAYS | B14: Days to settlement (feeds DF_USD/DF_FC via ACT/360) | C14: Days | D14: 365 | E14: Actual days from trade date to settlement date
A16: Derived Accumulation Factors
A17: Named Range | B17: Description | C17: Unit | D17: Value | E17: Formula
A18: DF_USD | B18: USD accumulation factor | C18: factor | D18: =1+R_USD*T_DAYS/360 -> 1.0408597 | E18: 1+R_USD × T_DAYS/360 (ACT/360, per spec §4/§5 Step 0)
A19: DF_FC | B19: EUR accumulation factor | C19: factor | D19: =1+R_FC*T_DAYS/360 -> 1.0292 | E19: 1+R_FC × T_DAYS/360 (ACT/360, per spec §4/§5 Step 0)
A21: Modeling Assumption
A22: Named Range | B22: Description | C22: Unit | D22: Value | E22: Notes
A23: STEP_PCT | B23: Sensitivity grid step size (±5% in 1% steps, 11 points) | C23: % | D23: 0.01 | E23: Single input driving the whole sensitivity grid — change here to reshape every grid tab
A25: ✓ FC_AMT confirmed: $4,500,000 is today's USD-equivalent value of the receivable, translated to EUR at S0_in (4,500,000 / 1.1400 ≈ €3,947,368).

Sheet Forward
A1: Step 1 — Forward Hedge
A2: Locked at inception; constant across the sensitivity grid.
A4: Named Range | B4: Description | C4: Value | D4: Formula
A5: USD_FWD | B5: USD proceeds locked in via forward contract | C5: =FC_AMT*F0_in -> 4292762.7 | D5: FC_AMT × F0_in

Sheet MoneyMarket
A1: Step 2 — Money-Market Hedge
A2: Three-step replication of the forward using the company's own USD/EUR funding and investment rates, plus the covered-interest-parity check.
A4: Named Range | B4: Description | C4: Value | D4: Formula
A5: BORROW_EUR | B5: Step 2a — Borrow EUR today, sized so the receivable exactly repays the loan at settlement | C5: =FC_AMT/DF_FC -> 3835375 | D5: FC_AMT / DF_FC
A6: USD_NOW | B6: Step 2b — Convert borrowed EUR to USD at spot | C6: =BORROW_EUR*S0_in -> 4372327.6 | D6: BORROW_EUR × S0_in
A7: USD_MM | B7: Step 2c — Invest USD proceeds at R_USD to settlement | C7: =USD_NOW*DF_USD -> 4550979.6 | D7: USD_now × DF_USD
A9: Parity Check
A10: Named Range | B10: Description | C10: Value | D10: Formula
A11: F_IMPLIED | B11: Forward implied by covered interest-rate parity — should ≈ F0_in | C11: =S0_in*DF_USD/DF_FC -> 1.152915 | D11: S0_in × DF_USD / DF_FC
A12: PARITY_GAP | B12: F_IMPLIED − F0_in (documented gap, not treated as a formula error) | C12: =F_IMPLIED-F0_in -> 0.065414966
A14: Note: at the placeholder rates in the Inputs tab, parity implies a forward near 1.153, materially above the counterparty's quoted F0_in of 1.0875. This gap is carried forward from the Stage 1 memo as an open item — verify the quoted forward before execution rather than treating this check as evidence of a formula error.

Sheet Options
A1: Steps 3–4 — Protective Put & Collar
A2: Protective put (put purchased) and collar (put purchased + call sold) payoffs across the settlement-spot grid.
A4: Named Range | B4: Description | C4: Value | D4: Formula
A5: FV_PREM_PUT | B5: Future value of put premium paid, carried to settlement at R_USD | C5: =-PREM_PUT*FC_AMT*DF_USD -> -61629.845 | D5: -PREM_PUT × FC_AMT × DF_USD
A6: FV_NET_PREM_COLLAR | B6: Future value of net premium (call received − put paid), carried to settlement | C6: =(PREM_CALL-PREM_PUT)*FC_AMT*DF_USD -> 12325.969 | D6: (PREM_CALL − PREM_PUT) × FC_AMT × DF_USD
A8: Settlement-Spot Grid
A9: Idx | B9: S_T | C9: USD_PUT(S_T) | D9: USD_COLLAR(S_T)
A10: -5 | B10: =S0_in*(1+A10*STEP_PCT) -> 1.083 | C10: =MAX(B10,K_PUT)*FC_AMT+FV_PREM_PUT -> 4438369.7 | D10: =MIN(MAX(B10,K_PUT),K_CALL)*FC_AMT+FV_NET_PREM_COLLAR -> 4512325.5
A11: -4 | B11: =S0_in*(1+A11*STEP_PCT) -> 1.0944 | C11: =MAX(B11,K_PUT)*FC_AMT+FV_PREM_PUT -> 4438369.7 | D11: =MIN(MAX(B11,K_PUT),K_CALL)*FC_AMT+FV_NET_PREM_COLLAR -> 4512325.5
A12: -3 | B12: =S0_in*(1+A12*STEP_PCT) -> 1.1058 | C12: =MAX(B12,K_PUT)*FC_AMT+FV_PREM_PUT -> 4438369.7 | D12: =MIN(MAX(B12,K_PUT),K_CALL)*FC_AMT+FV_NET_PREM_COLLAR -> 4512325.5
A13: -2 | B13: =S0_in*(1+A13*STEP_PCT) -> 1.1172 | C13: =MAX(B13,K_PUT)*FC_AMT+FV_PREM_PUT -> 4438369.7 | D13: =MIN(MAX(B13,K_PUT),K_CALL)*FC_AMT+FV_NET_PREM_COLLAR -> 4512325.5
A14: -1 | B14: =S0_in*(1+A14*STEP_PCT) -> 1.1286 | C14: =MAX(B14,K_PUT)*FC_AMT+FV_PREM_PUT -> 4438369.7 | D14: =MIN(MAX(B14,K_PUT),K_CALL)*FC_AMT+FV_NET_PREM_COLLAR -> 4512325.5
A15: 0 | B15: =S0_in*(1+A15*STEP_PCT) -> 1.14 | C15: =MAX(B15,K_PUT)*FC_AMT+FV_PREM_PUT -> 4438369.7 | D15: =MIN(MAX(B15,K_PUT),K_CALL)*FC_AMT+FV_NET_PREM_COLLAR -> 4512325.5
A16: 1 | B16: =S0_in*(1+A16*STEP_PCT) -> 1.1514 | C16: =MAX(B16,K_PUT)*FC_AMT+FV_PREM_PUT -> 4483369.7 | D16: =MIN(MAX(B16,K_PUT),K_CALL)*FC_AMT+FV_NET_PREM_COLLAR -> 4512325.5
A17: 2 | B17: =S0_in*(1+A17*STEP_PCT) -> 1.1628 | C17: =MAX(B17,K_PUT)*FC_AMT+FV_PREM_PUT -> 4528369.7 | D17: =MIN(MAX(B17,K_PUT),K_CALL)*FC_AMT+FV_NET_PREM_COLLAR -> 4512325.5
A18: 3 | B18: =S0_in*(1+A18*STEP_PCT) -> 1.1742 | C18: =MAX(B18,K_PUT)*FC_AMT+FV_PREM_PUT -> 4573369.7 | D18: =MIN(MAX(B18,K_PUT),K_CALL)*FC_AMT+FV_NET_PREM_COLLAR -> 4512325.5
A19: 4 | B19: =S0_in*(1+A19*STEP_PCT) -> 1.1856 | C19: =MAX(B19,K_PUT)*FC_AMT+FV_PREM_PUT -> 4618369.7 | D19: =MIN(MAX(B19,K_PUT),K_CALL)*FC_AMT+FV_NET_PREM_COLLAR -> 4512325.5
A20: 5 | B20: =S0_in*(1+A20*STEP_PCT) -> 1.197 | C20: =MAX(B20,K_PUT)*FC_AMT+FV_PREM_PUT -> 4663369.7 | D20: =MIN(MAX(B20,K_PUT),K_CALL)*FC_AMT+FV_NET_PREM_COLLAR -> 4512325.5
A22: Named Range | B22: Description | C22: Value | D22: Formula
A23: USD_PUT_BASE | B23: Protective put proceeds at baseline (S_T = S0_in) | C23: =C15 -> 4438369.7 | D23: grid row where Idx=0 (row 15)
A24: USD_PUT_FLOOR | B24: Worst-case put proceeds across the grid | C24: =MIN(C10:C20) -> 4438369.7 | D24: MIN(USD_PUT(S_T) grid)
A25: USD_COLLAR_BASE | B25: Collar proceeds at baseline (S_T = S0_in) | C25: =D15 -> 4512325.5 | D25: grid row where Idx=0 (row 15)

Sheet Sensitivity
A1: Consolidated Sensitivity — All Strategies
A2: ±5% grid around S0_in, 1% steps (Inputs!STEP_PCT). USD_FWD and USD_MM are constants; USD_PUT and USD_COLLAR link to the Options tab grid.
A4: Strategy Summary (Base Case, S_T = S0_in)
A5: Strategy | B5: Base-Case USD Proceeds | C5: Hedge Profit vs No Hedge
A6: No Hedge | B6: =FC_AMT*S0_in -> 4499999.5 | C6: 0
A7: Forward | B7: =USD_FWD -> 4292762.7 | C7: =B7-B6 -> -207236.82
A8: Money Market | B8: =USD_MM -> 4550979.6 | C8: =B8-B6 -> 50980.125
A9: Protective Put | B9: =USD_PUT_BASE -> 4438369.7 | C9: =B9-B6 -> -61629.845
A10: Collar | B10: =USD_COLLAR_BASE -> 4512325.5 | C10: =B10-B6 -> 12325.969
A12: Sensitivity Grid & Chart Data
A13: Idx | B13: S_T | C13: No Hedge | D13: Forward | E13: Money Market | F13: Protective Put | G13: Collar | H13: Profit: Fwd | I13: Profit: MM | J13: Profit: Put | K13: Profit: Collar | L13: Best (All) | M13: Best (Active Hedges)
A14: -5 | B14: =Options!B10 -> 1.083 | C14: =B14*FC_AMT -> 4274999.5 | D14: =USD_FWD -> 4292762.7 | E14: =USD_MM -> 4550979.6 | F14: =Options!C10 -> 4438369.7 | G14: =Options!D10 -> 4512325.5 | H14: =D14-C14 -> 17763.156 | I14: =E14-C14 -> 275980.1 | J14: =F14-C14 -> 163370.13 | K14: =G14-C14 -> 237325.95 | L14: =INDEX($C$13:$G$13,MATCH(MAX(C14:G14),C14:G14,0)) -> Money Market | M14: =INDEX($D$13:$G$13,MATCH(MAX(D14:G14),D14:G14,0)) -> Money Market
A15: -4 | B15: =Options!B11 -> 1.0944 | C15: =B15*FC_AMT -> 4319999.5 | D15: =USD_FWD -> 4292762.7 | E15: =USD_MM -> 4550979.6 | F15: =Options!C11 -> 4438369.7 | G15: =Options!D11 -> 4512325.5 | H15: =D15-C15 -> -27236.839 | I15: =E15-C15 -> 230980.11 | J15: =F15-C15 -> 118370.14 | K15: =G15-C15 -> 192325.95 | L15: =INDEX($C$13:$G$13,MATCH(MAX(C15:G15),C15:G15,0)) -> Money Market | M15: =INDEX($D$13:$G$13,MATCH(MAX(D15:G15),D15:G15,0)) -> Money Market
A16: -3 | B16: =Options!B12 -> 1.1058 | C16: =B16*FC_AMT -> 4364999.5 | D16: =USD_FWD -> 4292762.7 | E16: =USD_MM -> 4550979.6 | F16: =Options!C12 -> 4438369.7 | G16: =Options!D12 -> 4512325.5 | H16: =D16-C16 -> -72236.834 | I16: =E16-C16 -> 185980.11 | J16: =F16-C16 -> 73370.14 | K16: =G16-C16 -> 147325.95 | L16: =INDEX($C$13:$G$13,MATCH(MAX(C16:G16),C16:G16,0)) -> Money Market | M16: =INDEX($D$13:$G$13,MATCH(MAX(D16:G16),D16:G16,0)) -> Money Market
A17: -2 | B17: =Options!B13 -> 1.1172 | C17: =B17*FC_AMT -> 4409999.5 | D17: =USD_FWD -> 4292762.7 | E17: =USD_MM -> 4550979.6 | F17: =Options!C13 -> 4438369.7 | G17: =Options!D13 -> 4512325.5 | H17: =D17-C17 -> -117236.83 | I17: =E17-C17 -> 140980.12 | J17: =F17-C17 -> 28370.145 | K17: =G17-C17 -> 102325.96 | L17: =INDEX($C$13:$G$13,MATCH(MAX(C17:G17),C17:G17,0)) -> Money Market | M17: =INDEX($D$13:$G$13,MATCH(MAX(D17:G17),D17:G17,0)) -> Money Market
A18: -1 | B18: =Options!B14 -> 1.1286 | C18: =B18*FC_AMT -> 4454999.5 | D18: =USD_FWD -> 4292762.7 | E18: =USD_MM -> 4550979.6 | F18: =Options!C14 -> 4438369.7 | G18: =Options!D14 -> 4512325.5 | H18: =D18-C18 -> -162236.82 | I18: =E18-C18 -> 95980.12 | J18: =F18-C18 -> -16629.85 | K18: =G18-C18 -> 57325.964 | L18: =INDEX($C$13:$G$13,MATCH(MAX(C18:G18),C18:G18,0)) -> Money Market | M18: =INDEX($D$13:$G$13,MATCH(MAX(D18:G18),D18:G18,0)) -> Money Market
A19: 0 | B19: =Options!B15 -> 1.14 | C19: =B19*FC_AMT -> 4499999.5 | D19: =USD_FWD -> 4292762.7 | E19: =USD_MM -> 4550979.6 | F19: =Options!C15 -> 4438369.7 | G19: =Options!D15 -> 4512325.5 | H19: =D19-C19 -> -207236.82 | I19: =E19-C19 -> 50980.125 | J19: =F19-C19 -> -61629.845 | K19: =G19-C19 -> 12325.969 | L19: =INDEX($C$13:$G$13,MATCH(MAX(C19:G19),C19:G19,0)) -> Money Market | M19: =INDEX($D$13:$G$13,MATCH(MAX(D19:G19),D19:G19,0)) -> Money Market
A20: 1 | B20: =Options!B16 -> 1.1514 | C20: =B20*FC_AMT -> 4544999.5 | D20: =USD_FWD -> 4292762.7 | E20: =USD_MM -> 4550979.6 | F20: =Options!C16 -> 4483369.7 | G20: =Options!D16 -> 4512325.5 | H20: =D20-C20 -> -252236.82 | I20: =E20-C20 -> 5980.1296 | J20: =F20-C20 -> -61629.845 | K20: =G20-C20 -> -32674.026 | L20: =INDEX($C$13:$G$13,MATCH(MAX(C20:G20),C20:G20,0)) -> Money Market | M20: =INDEX($D$13:$G$13,MATCH(MAX(D20:G20),D20:G20,0)) -> Money Market
A21: 2 | B21: =Options!B17 -> 1.1628 | C21: =B21*FC_AMT -> 4589999.5 | D21: =USD_FWD -> 4292762.7 | E21: =USD_MM -> 4550979.6 | F21: =Options!C17 -> 4528369.7 | G21: =Options!D17 -> 4512325.5 | H21: =D21-C21 -> -297236.81 | I21: =E21-C21 -> -39019.866 | J21: =F21-C21 -> -61629.845 | K21: =G21-C21 -> -77674.021 | L21: =INDEX($C$13:$G$13,MATCH(MAX(C21:G21),C21:G21,0)) -> No Hedge | M21: =INDEX($D$13:$G$13,MATCH(MAX(D21:G21),D21:G21,0)) -> Money Market
A22: 3 | B22: =Options!B18 -> 1.1742 | C22: =B22*FC_AMT -> 4634999.5 | D22: =USD_FWD -> 4292762.7 | E22: =USD_MM -> 4550979.6 | F22: =Options!C18 -> 4573369.7 | G22: =Options!D18 -> 4512325.5 | H22: =D22-C22 -> -342236.81 | I22: =E22-C22 -> -84019.861 | J22: =F22-C22 -> -61629.845 | K22: =G22-C22 -> -122674.02 | L22: =INDEX($C$13:$G$13,MATCH(MAX(C22:G22),C22:G22,0)) -> No Hedge | M22: =INDEX($D$13:$G$13,MATCH(MAX(D22:G22),D22:G22,0)) -> Protective Put
A23: 4 | B23: =Options!B19 -> 1.1856 | C23: =B23*FC_AMT -> 4679999.5 | D23: =USD_FWD -> 4292762.7 | E23: =USD_MM -> 4550979.6 | F23: =Options!C19 -> 4618369.7 | G23: =Options!D19 -> 4512325.5 | H23: =D23-C23 -> -387236.8 | I23: =E23-C23 -> -129019.86 | J23: =F23-C23 -> -61629.845 | K23: =G23-C23 -> -167674.01 | L23: =INDEX($C$13:$G$13,MATCH(MAX(C23:G23),C23:G23,0)) -> No Hedge | M23: =INDEX($D$13:$G$13,MATCH(MAX(D23:G23),D23:G23,0)) -> Protective Put
A24: 5 | B24: =Options!B20 -> 1.197 | C24: =B24*FC_AMT -> 4724999.5 | D24: =USD_FWD -> 4292762.7 | E24: =USD_MM -> 4550979.6 | F24: =Options!C20 -> 4663369.7 | G24: =Options!D20 -> 4512325.5 | H24: =D24-C24 -> -432236.8 | I24: =E24-C24 -> -174019.85 | J24: =F24-C24 -> -61629.845 | K24: =G24-C24 -> -212674.01 | L24: =INDEX($C$13:$G$13,MATCH(MAX(C24:G24),C24:G24,0)) -> No Hedge | M24: =INDEX($D$13:$G$13,MATCH(MAX(D24:G24),D24:G24,0)) -> Protective Put

Sheet Notes-Assumptions
A1: Notes & Assumptions
A3: Quote Convention
A4: All rates are USD per EUR; a higher quote means EUR appreciation.
A6: Rate Basis
A7: ACT/360 applied to both legs — DF_USD = 1+R_USD×T_DAYS/360 and DF_FC = 1+R_FC×T_DAYS/360, per spec §4/§5 Step 0. A more rigorous build would split BASIS_USD/BASIS_FC if EUR-side convention differs; flagged rather than built, per scope.
A9: Horizon
A10: Single-maturity model, T_DAYS = 365. No partial-year or multi-tranche hedging.
A12: Parity Expectation
A13: The money-market hedge is assumed to replicate the forward hedge under covered interest-rate parity. At the placeholder rates, parity implies a forward near 1.153, materially above the counterparty's quoted F0_in of 1.0875. This gap is carried forward from the Stage 1 memo as an open item — verify the quoted forward before execution rather than treating the model's parity check as evidence of a formula error.
A15: Premium Treatment
A16: Option premiums are paid (put) or received (call) upfront in USD, quoted per 1 unit of FC, no contract multiplier. Premiums are carried forward to the settlement date at R_USD so they sit on the same footing as settlement-date proceeds.
A18: Collar Structure
... A31: 1. FC_AMT — CONFIRMED: $4,500,000 today's value / spot (1.14) = €3,947,368. 2. Forward-vs-parity gap — verify the counterparty's quoted forward rather than assuming a model error. 3. Rate basis simplified to single ACT/360 for both legs; revisit if EUR-side convention differs materially at execution.
